Metadata-Version: 2.1
Name: dts
Version: 0.1.3
Summary: Generate sequence of datatimes, like seq
Home-page: https://github.com/KwangYeol/dts
Author: Kwangyeol Ryu
Author-email: kwangyeolryu@gmail.com
License: UNKNOWN
Project-URL: Bug Reports, https://github.com/KwangYeol/dts/issues
Project-URL: Source, https://github.com/KwangYeol/dts
Keywords: dts seq datetime generator
Platform: UNKNOWN
Classifier: Development Status :: 4 - Beta
Classifier: Environment :: Console
Classifier: Intended Audience :: Developers
Classifier: Intended Audience :: System Administrators
Classifier: Topic :: Software Development :: Build Tools
Classifier: License :: OSI Approved :: Apache Software License
Classifier: Programming Language :: Python :: 2.7
Classifier: Programming Language :: Python :: 3.4
Classifier: Programming Language :: Python :: 3.5
Classifier: Programming Language :: Python :: 3.6
